apt_toolkit/__init__.py
apt_toolkit/__main__.py
apt_toolkit/american_targets.py
apt_toolkit/american_targets_enhanced.py
apt_toolkit/campaign.py
apt_toolkit/campaign_logging.py
apt_toolkit/catalog.py
apt_toolkit/cli.py
apt_toolkit/cli_enhanced.py
apt_toolkit/cli_new.py
apt_toolkit/cli_root.py
apt_toolkit/command_control.py
apt_toolkit/command_control_real.py
apt_toolkit/deepseek_integration.py
apt_toolkit/defense_evasion.py
apt_toolkit/defense_evasion_enhanced.py
apt_toolkit/defense_evasion_real.py
apt_toolkit/email_repository.py
apt_toolkit/exfiltration.py
apt_toolkit/exploit_intel.py
apt_toolkit/financial_targeting.py
apt_toolkit/financial_theft_methods.py
apt_toolkit/hardware_disruption.py
apt_toolkit/initial_access.py
apt_toolkit/initial_access_enhanced.py
apt_toolkit/initial_access_real.py
apt_toolkit/interactive_shell.py
apt_toolkit/lateral_movement.py
apt_toolkit/offensive_playbooks.py
apt_toolkit/organization_manager.py
apt_toolkit/persistence.py
apt_toolkit/persistence_enhanced.py
apt_toolkit/phishing.py
apt_toolkit/privilege_escalation.py
apt_toolkit/privilege_escalation_enhanced.py
apt_toolkit/real_campaign_orchestrator.py
apt_toolkit/real_tao.py
apt_toolkit/settings_manager.py
apt_toolkit/uk_targets.py
apt_toolkit/uk_targets_enhanced.py
apt_toolkit/chinese_apt_campaign/__init__.py
apt_toolkit/chinese_apt_campaign/advanced_targeting.py
apt_toolkit/chinese_apt_campaign/c2_server.py
apt_toolkit/chinese_apt_campaign/campaign_orchestrator.py
apt_toolkit/chinese_apt_campaign/custom_backdoor.py
apt_toolkit/chinese_apt_campaign/demo.py
apt_toolkit/chinese_apt_campaign/spear_phishing_generator.py
apt_toolkit/chinese_apt_campaign/system_exploitation.py
apt_toolkit-3.3.2.dist-info/licenses/LICENSE
scripts/__init__.py
scripts/ensure_campaign_tools.py
scripts/execute_extensive_campaigns.py
scripts/extensive_campaign_orchestrator.py
scripts/real_target_campaign_runner.py
scripts/red_team_real_targets_runner.py
scripts/run_chinese_national_security_campaign.py
scripts/split_unique_emails_db.py
apt_toolkit-3.3.2.dist-info/METADATA
apt_toolkit-3.3.2.dist-info/WHEEL
apt_toolkit-3.3.2.dist-info/entry_points.txt
apt_toolkit-3.3.2.dist-info/top_level.txt
apt_toolkit-3.3.2.dist-info/RECORD
